README.md
setup.cfg
setup.py
wwpdb/__init__.py
wwpdb.apps.ccmodule.egg-info/PKG-INFO
wwpdb.apps.ccmodule.egg-info/SOURCES.txt
wwpdb.apps.ccmodule.egg-info/dependency_links.txt
wwpdb.apps.ccmodule.egg-info/not-zip-safe
wwpdb.apps.ccmodule.egg-info/requires.txt
wwpdb.apps.ccmodule.egg-info/top_level.txt
wwpdb/apps/__init__.py
wwpdb/apps/ccmodule/__init__.py
wwpdb/apps/ccmodule/chem/ChemCompAnnotate.py
wwpdb/apps/ccmodule/chem/ChemCompAssign.py
wwpdb/apps/ccmodule/chem/ChemCompAssignDepict.py
wwpdb/apps/ccmodule/chem/ChemCompAssignDepictLite.py
wwpdb/apps/ccmodule/chem/PdbxChemCompAssign.py
wwpdb/apps/ccmodule/chem/__init__.py
wwpdb/apps/ccmodule/depict/ChemCompDepict.py
wwpdb/apps/ccmodule/depict/__init__.py
wwpdb/apps/ccmodule/extract/__init__.py
wwpdb/apps/ccmodule/extract/ccOps.py
wwpdb/apps/ccmodule/io/ChemCompAssignDataStore.py
wwpdb/apps/ccmodule/io/ChemCompDataExport.py
wwpdb/apps/ccmodule/io/ChemCompDataImport.py
wwpdb/apps/ccmodule/io/ChemCompEditStore.py
wwpdb/apps/ccmodule/io/ChemCompIo.py
wwpdb/apps/ccmodule/io/__init__.py
wwpdb/apps/ccmodule/reports/ChemCompAlignImageGenerator.py
wwpdb/apps/ccmodule/reports/ChemCompAlignImages.py
wwpdb/apps/ccmodule/reports/ChemCompBigAlignImages.py
wwpdb/apps/ccmodule/reports/ChemCompGenImage.py
wwpdb/apps/ccmodule/reports/ChemCompReports.py
wwpdb/apps/ccmodule/reports/InstanceDataGenerator.py
wwpdb/apps/ccmodule/reports/__init__.py
wwpdb/apps/ccmodule/search/ChemCompSearch.py
wwpdb/apps/ccmodule/search/ChemCompSearchDb.py
wwpdb/apps/ccmodule/search/ChemCompSearchDbDepict.py
wwpdb/apps/ccmodule/search/ChemCompSearchDepict.py
wwpdb/apps/ccmodule/search/DbSession.py
wwpdb/apps/ccmodule/search/__init__.py
wwpdb/apps/ccmodule/sketch/ChemCompSketch.py
wwpdb/apps/ccmodule/sketch/ChemCompSketchDepict.py
wwpdb/apps/ccmodule/sketch/__init__.py
wwpdb/apps/ccmodule/utils/ChemCompConfig.py
wwpdb/apps/ccmodule/utils/ChemCompDpUtility.py
wwpdb/apps/ccmodule/utils/ChemCompWFInterface.py
wwpdb/apps/ccmodule/utils/Exceptions.py
wwpdb/apps/ccmodule/utils/LigandAnalysisState.py
wwpdb/apps/ccmodule/utils/__init__.py
wwpdb/apps/ccmodule/view/ChemCompView.py
wwpdb/apps/ccmodule/view/ChemCompViewDepict.py
wwpdb/apps/ccmodule/view/__init__.py
wwpdb/apps/ccmodule/webapp/ChemCompWebApp.py
