Metadata-Version: 2.4
Name: wwpdb.apps.ccmodule
Version: 0.33.3
Summary: wwPDB workflow engine utils
Home-page: https://github.com/rcsb/py-wwpdb_apps_wf_engine_utils
Author: Ezra Peisach
Author-email: ezra.peisach@rcsb.org
License: Apache 2.0
Classifier: Development Status :: 3 - Alpha
Classifier: Intended Audience :: Developers
Classifier: Natural Language :: English
Classifier: License :: OSI Approved :: Apache Software License
Classifier: Programming Language :: Python
Classifier: Programming Language :: Python :: 2.7
Classifier: Programming Language :: Python :: 3
Classifier: Programming Language :: Python :: 3.6
Classifier: Programming Language :: Python :: 3.7
Requires-Dist: mmcif
Requires-Dist: mmcif.utils>=0.13
Requires-Dist: wwpdb.utils.config~=0.34
Requires-Dist: wwpdb.utils.dp>=0.11
Requires-Dist: rcsb.utils.multiproc
Requires-Dist: wwpdb.utils.wf
Requires-Dist: wwpdb.utils.session>=0.2
Requires-Dist: mysqlclient
Requires-Dist: wwpdb.io<2.0,>=0.35
Provides-Extra: consumer
Requires-Dist: wwpdb.utils.oe_util>=0.2; extra == "consumer"
Provides-Extra: dev
Requires-Dist: check-manifest; extra == "dev"
Provides-Extra: test
Requires-Dist: coverage; extra == "test"
Provides-Extra: server
Requires-Dist: webob; extra == "server"
Dynamic: author
Dynamic: author-email
Dynamic: classifier
Dynamic: description
Dynamic: home-page
Dynamic: license
Dynamic: provides-extra
Dynamic: requires-dist
Dynamic: summary
